tree_sitter_css/__init__.py
tree_sitter_css/__init__.pyi
tree_sitter_css/_binding.abi3.so
tree_sitter_css/binding.c
tree_sitter_css/py.typed
tree_sitter_css/queries/highlights.scm
tree_sitter_css-0.25.0.dist-info/METADATA
tree_sitter_css-0.25.0.dist-info/WHEEL
tree_sitter_css-0.25.0.dist-info/top_level.txt
tree_sitter_css-0.25.0.dist-info/RECORD
tree_sitter_css-0.25.0.dist-info/licenses/LICENSE
