Metadata-Version: 2.1
Name: tree-sitter-css
Version: 0.25.0
Summary: CSS grammar for tree-sitter
Author-email: Max Brunsfeld <maxbrunsfeld@gmail.com>, Amaan Qureshi <contact@amaanq.com>
License: MIT
Project-URL: Homepage, https://github.com/tree-sitter/tree-sitter-css
Project-URL: Funding, https://github.com/sponsors/tree-sitter
Keywords: incremental,parsing,tree-sitter,css
Classifier: Intended Audience :: Developers
Classifier: Topic :: Software Development :: Compilers
Classifier: Topic :: Text Processing :: Linguistic
Classifier: Typing :: Typed
Requires-Python: >=3.10
License-File: LICENSE
Provides-Extra: core
Requires-Dist: tree-sitter~=0.24; extra == "core"
